byemail/__init__.py
byemail/account.py
byemail/commands.py
byemail/conf.py
byemail/default_settings.py
byemail/httpserver.py
byemail/mailutils.py
byemail/push.py
byemail/settings_tpl.py
byemail/smtp.py
byemail/client/dist/favicon.ico
byemail/client/dist/index.html
byemail/client/dist/manifest.json
byemail/client/dist/precache-manifest.c2f0b8cdf710c22b311ad8b4c4de1f29.js
byemail/client/dist/robots.txt
byemail/client/dist/service-worker.js
byemail/client/dist/css/app.091cc9dd.css
byemail/client/dist/css/chunk-vendors.9daa6be5.css
byemail/client/dist/img/icons/android-chrome-192x192.png
byemail/client/dist/img/icons/android-chrome-512x512.png
byemail/client/dist/img/icons/apple-touch-icon-120x120.png
byemail/client/dist/img/icons/apple-touch-icon-152x152.png
byemail/client/dist/img/icons/apple-touch-icon-180x180.png
byemail/client/dist/img/icons/apple-touch-icon-60x60.png
byemail/client/dist/img/icons/apple-touch-icon-76x76.png
byemail/client/dist/img/icons/apple-touch-icon.png
byemail/client/dist/img/icons/favicon-16x16.png
byemail/client/dist/img/icons/favicon-32x32.png
byemail/client/dist/img/icons/msapplication-icon-144x144.png
byemail/client/dist/img/icons/mstile-150x150.png
byemail/client/dist/img/icons/safari-pinned-tab.svg
byemail/client/dist/js/app.fc1ebabd.js
byemail/client/dist/js/app.fc1ebabd.js.map
byemail/client/dist/js/chunk-vendors.9064ce4a.js
byemail/client/dist/js/chunk-vendors.9064ce4a.js.map
byemail/helpers/reloader.py
byemail/middlewares/dkim.py
byemail/storage/__init__.py
byemail/storage/core.py
byemail/storage/sqldb.py
byemail/storage/tinydb.py
byemail-0.0.1.dist-info/LICENSE
byemail-0.0.1.dist-info/METADATA
byemail-0.0.1.dist-info/WHEEL
byemail-0.0.1.dist-info/entry_points.txt
byemail-0.0.1.dist-info/top_level.txt
byemail-0.0.1.dist-info/RECORD
