Metadata-Version: 2.1
Name: byemail
Version: 0.0.1
Summary: byemail
Home-page: UNKNOWN
Author: Jeremie Pardou
Author-email: jeremie.pardou@mhcomm.fr
License: Apache Software License
Keywords: mail asyncio smtp webmail
Platform: UNKNOWN
Classifier: Development Status :: 4 - Beta
Classifier: License :: OSI Approved :: Apache Software License
Classifier: Programming Language :: Python :: 3.5
Classifier: Programming Language :: Python :: 3.6
Classifier: Programming Language :: Python :: 3 :: Only
Classifier: Operating System :: POSIX :: Linux
Classifier: Topic :: Internet
Classifier: Programming Language :: Python
Requires-Dist: begins
Requires-Dist: python-magic
Requires-Dist: aiosmtpd
Requires-Dist: arrow
Requires-Dist: ujson
Requires-Dist: aiodns
Requires-Dist: sanic
Requires-Dist: sanic-auth
Requires-Dist: tortoise-orm
Requires-Dist: py-vapid
Requires-Dist: pywebpush
Requires-Dist: uvloop
